dalle3/__init__.py
dalle3/dalle.py
dalle3/idea2image.py
dalle3-0.0.9.dist-info/LICENSE
dalle3-0.0.9.dist-info/WHEEL
dalle3-0.0.9.dist-info/METADATA
dalle3-0.0.9.dist-info/RECORD
