Metadata-Version: 2.1
Name: dalle3
Version: 0.0.9
Summary: dalle3 - Pytorch
Home-page: https://github.com/Agora-X/DALLE3-API
License: MIT
Keywords: artificial intelligence,deep learning,optimizers,Prompt Engineering
Author: Kye Gomez
Author-email: kye@apac.ai
Requires-Python: >=3.6,<4.0
Classifier: Development Status :: 4 - Beta
Classifier: Intended Audience :: Developers
Classifier: License :: OSI Approved :: MIT License
Classifier: Programming Language :: Python :: 3
Classifier: Programming Language :: Python :: 3.6
Classifier: Programming Language :: Python :: 3.7
Classifier: Programming Language :: Python :: 3.8
Classifier: Programming Language :: Python :: 3.9
Classifier: Programming Language :: Python :: 3.10
Classifier: Programming Language :: Python :: 3.11
Classifier: Programming Language :: Python :: 3.6
Classifier: Topic :: Scientific/Engineering :: Artificial Intelligence
Requires-Dist: pandas
Requires-Dist: requests
Requires-Dist: selenium
Requires-Dist: swarms
Requires-Dist: undetected-chromedriver
Project-URL: Repository, https://github.com/Agora-X/DALLE3-API
